[{"Ranking":"1","Title":"Supernova","Artist":"aespa"},{"Ranking":"2","Title":"Supernatural","Artist":"NewJeans"},{"Ranking":"3","Title":"Sticky","Artist":"KISS OF LIFE"},{"Ranking":"4","Title":"How Sweet","Artist":"NewJeans"},{"Ranking":"5","Title":"클락션 (Klaxon)","Artist":"(여자)아이들"},{"Ranking":"6","Title":"Armageddon","Artist":"aespa"},{"Ranking":"7","Title":"Bubble Gum","Artist":"NewJeans"},{"Ranking":"8","Title":"Welcome to the Show","Artist":"DAY6 (데이식스)"},{"Ranking":"9","Title":"Small girl (feat. 도경수(D.O.))","Artist":"이영지"},{"Ranking":"10","Title":"한 페이지가 될 수 있게","Artist":"DAY6 (데이식스)"},{"Ranking":"11","Title":"고민중독","Artist":"QWER"},{"Ranking":"12","Title":"Magnetic","Artist":"아일릿(ILLIT)"},{"Ranking":"13","Title":"별별별 (See that?)","Artist":"NMIXX"},{"Ranking":"14","Title":"해야 (HEYA)","Artist":"IVE (아이브)"},{"Ranking":"15","Title":"소나기","Artist":"이클립스 (ECLIPSE)"},{"Ranking":"16","Title":"첫 만남은 계획대로 되지 않아","Artist":"TWS (투어스)"},{"Ranking":"17","Title":"Cosmic","Artist":"Red Velvet (레드벨벳)"},{"Ranking":"18","Title":"Supersonic","Artist":"프로미스나인"},{"Ranking":"19","Title":"나는 아픈 건 딱 질색이니까","Artist":"(여자)아이들"},{"Ranking":"20","Title":"내가 S면 넌 나의 N이 되어줘","Artist":"TWS (투어스)"},{"Ranking":"21","Title":"Boom Boom Bass","Artist":"RIIZE"},{"Ranking":"22","Title":"Hype Boy","Artist":"NewJeans"},{"Ranking":"23","Title":"예뻤어","Artist":"DAY6 (데이식스)"},{"Ranking":"24","Title":"SPOT! (feat. JENNIE)","Artist":"지코 (ZICO)"},{"Ranking":"25","Title":"Live My Life","Artist":"aespa"},{"Ranking":"26","Title":"삐그덕 (Walk)","Artist":"NCT 127"},{"Ranking":"27","Title":"Attention","Artist":"NewJeans"},{"Ranking":"28","Title":"에피소드","Artist":"이무진"},{"Ranking":"29","Title":"HAPPY","Artist":"DAY6 (데이식스)"},{"Ranking":"30","Title":"밤양갱","Artist":"비비(BIBI)"},{"Ranking":"31","Title":"천상연","Artist":"이창섭"},{"Ranking":"32","Title":"Cruel Summer","Artist":"Taylor Swift(테일러 스위프트)"},{"Ranking":"33","Title":"ETA","Artist":"NewJeans"},{"Ranking":"34","Title":"To. X","Artist":"태연 (TAEYEON)"},{"Ranking":"35","Title":"Chk Chk Boom","Artist":"Stray Kids (스트레이 키즈)"},{"Ranking":"36","Title":"Balloon in Love","Artist":"선미"},{"Ranking":"37","Title":"Ditto","Artist":"NewJeans"},{"Ranking":"38","Title":"Sexy In The Air","Artist":"태민 (TAEMIN)"},{"Ranking":"39","Title":"Right Now","Artist":"NewJeans"},{"Ranking":"40","Title":"I AM","Artist":"IVE (아이브)"},{"Ranking":"41","Title":"Love wins all","Artist":"아이유(IU)"},{"Ranking":"42","Title":"Super Shy","Artist":"NewJeans"},{"Ranking":"43","Title":"미안해 미워해 사랑해","Artist":"Crush"},{"Ranking":"44","Title":"네가 내 마음에 자리 잡았다 (Into You)","Artist":"엔플라잉(N.Flying)"},{"Ranking":"45","Title":"Accendio","Artist":"IVE (아이브)"},{"Ranking":"46","Title":"Love me or Leave me","Artist":"DAY6 (데이식스)"},{"Ranking":"47","Title":"Girls Never Die","Artist":"tripleS (트리플에스)"},{"Ranking":"48","Title":"비의 랩소디","Artist":"임재현"},{"Ranking":"49","Title":"처음 보는 나","Artist":"죠지"},{"Ranking":"50","Title":"Run Run","Artist":"이클립스 (ECLIPSE)"},{"Ranking":"51","Title":"Drama","Artist":"aespa"},{"Ranking":"52","Title":"Blue Moon","Artist":"엔플라잉(N.Flying)"},{"Ranking":"53","Title":"너의 모든 순간","Artist":"성시경"},{"Ranking":"54","Title":"OMG","Artist":"NewJeans"},{"Ranking":"55","Title":"오래된 노래","Artist":"허각"},{"Ranking":"56","Title":"ABCD","Artist":"나연 (TWICE)"},{"Ranking":"57","Title":"SHEESH","Artist":"BABYMONSTER"},{"Ranking":"58","Title":"Spicy","Artist":"aespa"},{"Ranking":"59","Title":"New Jeans","Artist":"NewJeans"},{"Ranking":"60","Title":"그랬나봐","Artist":"유회승 (엔플라잉)"},{"Ranking":"61","Title":"모든 날, 모든 순간 (Every day, Every Moment)","Artist":"폴킴(Paul Kim)"},{"Ranking":"62","Title":"Horizon","Artist":"태민 (TAEMIN)"},{"Ranking":"63","Title":"헤어지자 말해요","Artist":"박재정"},{"Ranking":"64","Title":"그대만 있다면 (여름날 우리 X 너드커넥션 (Nerd Connection))","Artist":"너드커넥션(Nerd Connection)"},{"Ranking":"65","Title":"LOVE DIVE","Artist":"IVE (아이브)"},{"Ranking":"66","Title":"사랑인가 봐","Artist":"멜로망스(MeloMance)"},{"Ranking":"67","Title":"사랑은 늘 도망가","Artist":"임영웅"},{"Ranking":"68","Title":"Popcorn","Artist":"도경수(D.O.)"},{"Ranking":"69","Title":"After LIKE","Artist":"IVE (아이브)"},{"Ranking":"70","Title":"숲","Artist":"최유리"},{"Ranking":"71","Title":"Steal The Show (From “엘리멘탈”)","Artist":"Lauv(라우브)"},{"Ranking":"72","Title":"주저하는 연인들을 위해","Artist":"잔나비"},{"Ranking":"73","Title":"Get A Guitar","Artist":"RIIZE"},{"Ranking":"74","Title":"인사","Artist":"범진"},{"Ranking":"75","Title":"Seven (feat. Latto) - Clean Ver.","Artist":"정국"},{"Ranking":"76","Title":"Love Lee","Artist":"AKMU(악뮤)"},{"Ranking":"77","Title":"Midas Touch","Artist":"KISS OF LIFE"},{"Ranking":"78","Title":"청혼하지 않을 이유를 못 찾았어","Artist":"이무진"},{"Ranking":"79","Title":"꿈","Artist":"태연 (TAEYEON)"},{"Ranking":"80","Title":"건물 사이에 피어난 장미 (Rose Blossom)","Artist":"H1-KEY (하이키)"},{"Ranking":"81","Title":"Lucky Girl Syndrome","Artist":"아일릿(ILLIT)"},{"Ranking":"82","Title":"WAY 4 LUV","Artist":"PLAVE"},{"Ranking":"83","Title":"You & Me","Artist":"제니 (JENNIE)"},{"Ranking":"84","Title":"홀씨","Artist":"아이유(IU)"},{"Ranking":"85","Title":"MANIAC","Artist":"VIVIZ (비비지)"},{"Ranking":"86","Title":"Star","Artist":"엔플라잉(N.Flying)"},{"Ranking":"87","Title":"사건의 지평선","Artist":"윤하(Younha\/ユンナ)"},{"Ranking":"88","Title":"버추얼 아이돌","Artist":"PLAVE"},{"Ranking":"89","Title":"후라이의 꿈","Artist":"AKMU(악뮤)"},{"Ranking":"90","Title":"Heaven","Artist":"태연 (TAEYEON)"},{"Ranking":"91","Title":"Perfect Night","Artist":"LE SSERAFIM (르세라핌)"},{"Ranking":"92","Title":"Kitsch","Artist":"IVE (아이브)"},{"Ranking":"93","Title":"I Don’t Think That I Like Her","Artist":"Charlie Puth(찰리 푸스)"},{"Ranking":"94","Title":"Love 119","Artist":"RIIZE"},{"Ranking":"95","Title":"G.O.A.T","Artist":"태민 (TAEMIN)"},{"Ranking":"96","Title":"우리 영화","Artist":"PLAVE"},{"Ranking":"97","Title":"봄눈","Artist":"10CM"},{"Ranking":"98","Title":"Impossible","Artist":"RIIZE"},{"Ranking":"99","Title":"Watch Me Woo!","Artist":"PLAVE"},{"Ranking":"100","Title":"MAESTRO","Artist":"세븐틴(SEVENTEEN)"}]